lxgp/__init__.py
lxgp-0.0.0.dist-info/METADATA
lxgp-0.0.0.dist-info/WHEEL
lxgp-0.0.0.dist-info/top_level.txt
lxgp-0.0.0.dist-info/RECORD
