Metadata-Version: 2.1
Name: lxgp
Version: 0.0.0
Summary: Atmospheric Chemistry Data Analysis Suite
Author-email: Ryan Fuller <ryan.a.fuller@jpl.nasa.gov>
